README.md
setup.py
scrapere/__init__.py
scrapere/browser_agents.txt
scrapere/toolbox.py
scrapere/user_agents.txt
scrapere.egg-info/PKG-INFO
scrapere.egg-info/SOURCES.txt
scrapere.egg-info/dependency_links.txt
scrapere.egg-info/requires.txt
scrapere.egg-info/top_level.txt