Metadata-Version: 2.1
Name: scrapere
Version: 0.3
Summary: Small set of my web scraping python tools
Home-page: https://github.com/vPere/scrapere
Author: vPere
License: MIT
Platform: UNKNOWN
